{
  "kind": "collectionType",
  "collectionName": "bpm_requests",
  "info": {
    "singularName": "bpm-request",
    "pluralName": "bpm-requests",
    "displayName": "BPM Request",
    "description": "Employee BPM requests and workflow state"
  },
  "options": {
    "draftAndPublish": false
  },
  "pluginOptions": {},
  "attributes": {
    "requestNumber": {
      "type": "string",
      "required": true,
      "unique": true
    },
    "type": {
      "type": "enumeration",
      "enum": [
        "PHYSICAL_PERSON",
        "HIRING",
        "PERSONNEL_TRANSFER",
        "DISMISSAL",
        "VACATION",
        "SICK_LEAVE",
        "DAY_OFF",
        "WEEKEND_WORK",
        "OVERTIME",
        "POSITION_COMBINATION",
        "TIMESHEET",
        "CHILDCARE_LEAVE",
        "CHILDCARE_RETURN",
        "VACATION_RECALL",
        "UNPAID_LEAVE",
        "BUSINESS_TRIP",
        "SCHEDULE_CHANGE",
        "MEMO",
        "TRAINING",
        "CERTIFICATE"
      ],
      "required": true
    },
    "integrationType": {
      "type": "integer",
      "min": 1,
      "max": 17
    },
    "templateVersion": {
      "type": "string",
      "default": "1.0"
    },
    "title": {
      "type": "string",
      "required": true
    },
    "status": {
      "type": "enumeration",
      "enum": [
        "DRAFT",
        "SUBMITTED",
        "MANAGER_REVIEW",
        "HR_REVIEW",
        "ACCOUNTING_REVIEW",
        "ONEC_PENDING",
        "ONEC_SENT",
        "COMPLETED",
        "REJECTED",
        "CANCELLED"
      ],
      "default": "SUBMITTED",
      "required": true
    },
    "workflowStage": {
      "type": "string"
    },
    "employeeIin": {
      "type": "string",
      "minLength": 12,
      "maxLength": 12
    },
    "employeeName": {
      "type": "string"
    },
    "employeePosition": {
      "type": "string"
    },
    "employeeDepartment": {
      "type": "string"
    },
    "employeeDepartmentId": {
      "type": "string"
    },
    "employeeOrganization": {
      "type": "string"
    },
    "employeeOrganizationId": {
      "type": "string"
    },
    "employeePersonnelNumber": {
      "type": "string"
    },
    "managerName": {
      "type": "string"
    },
    "managerPosition": {
      "type": "string"
    },
    "managerDepartment": {
      "type": "string"
    },
    "signingDirectorName": {
      "type": "string"
    },
    "signingDirectorPosition": {
      "type": "string"
    },
    "vacationType": {
      "type": "string"
    },
    "startDate": {
      "type": "date"
    },
    "endDate": {
      "type": "date"
    },
    "days": {
      "type": "integer"
    },
    "replacementEmployeeName": {
      "type": "string"
    },
    "comment": {
      "type": "text"
    },
    "history": {
      "type": "json",
      "default": []
    },
    "processData": {
      "type": "json",
      "default": {}
    },
    "onecPayload": {
      "type": "json"
    },
    "onecStatus": {
      "type": "enumeration",
      "enum": [
        "not_required",
        "pending",
        "sent",
        "error"
      ],
      "default": "pending"
    },
    "onecDocumentNumber": {
      "type": "string"
    },
    "onecResponse": {
      "type": "json"
    },
    "onecError": {
      "type": "text"
    },
    "submittedAt": {
      "type": "datetime"
    },
    "completedAt": {
      "type": "datetime"
    },
    "initiator": {
      "type": "relation",
      "relation": "manyToOne",
      "target": "plugin::users-permissions.user"
    },
    "employeeCard": {
      "type": "relation",
      "relation": "manyToOne",
      "target": "api::employee-card.employee-card"
    }
  }
}
